{
    "clientRefreshInterval": 300, 
    "gameList": [
        {
            "bannedChampions": [], 
            "gameId": 4053920108, 
            "gameLength": 69, 
            "gameMode": "ARAM", 
            "gameQueueConfigId": 450, 
            "gameStartTime": 1559680032355, 
            "gameType": "MATCHED_GAME", 
            "mapId": 12, 
            "observers": {
                "encryptionKey": "GA2QbDT5U8vhGCwbzq+muiloLip8QiSv"
            }, 
            "participants": [
                {
                    "bot": false, 
                    "championId": 102, 
                    "profileIconId": 2076, 
                    "spell1Id": 32, 
                    "spell2Id": 4, 
                    "summonerName": "cllo", 
                    "teamId": 100
                }, 
                {
                    "bot": false, 
                    "championId": 15, 
                    "profileIconId": 659, 
                    "spell1Id": 4, 
                    "spell2Id": 7, 
                    "summonerName": "Truecrowfather", 
                    "teamId": 100
                }, 
                {
                    "bot": false, 
                    "championId": 164, 
                    "profileIconId": 4086, 
                    "spell1Id": 32, 
                    "spell2Id": 4, 
                    "summonerName": "Juju 007", 
                    "teamId": 100
                }, 
                {
                    "bot": false, 
                    "championId": 8, 
                    "profileIconId": 508, 
                    "spell1Id": 32, 
                    "spell2Id": 4, 
                    "summonerName": "Ridethelight", 
                    "teamId": 100
                }, 
                {
                    "bot": false, 
                    "championId": 37, 
                    "profileIconId": 538, 
                    "spell1Id": 3, 
                    "spell2Id": 4, 
                    "summonerName": "legendaryBASH", 
                    "teamId": 100
                }, 
                {
                    "bot": false, 
                    "championId": 202, 
                    "profileIconId": 3461, 
                    "spell1Id": 7, 
                    "spell2Id": 4, 
                    "summonerName": "Showfield", 
                    "teamId": 200
                }, 
                {
                    "bot": false, 
                    "championId": 84, 
                    "profileIconId": 1200, 
                    "spell1Id": 4, 
                    "spell2Id": 14, 
                    "summonerName": "oVeNGaDoR", 
                    "teamId": 200
                }, 
                {
                    "bot": false, 
                    "championId": 53, 
                    "profileIconId": 3155, 
                    "spell1Id": 4, 
                    "spell2Id": 32, 
                    "summonerName": "Daemonpies", 
                    "teamId": 200
                }, 
                {
                    "bot": false, 
                    "championId": 157, 
                    "profileIconId": 15, 
                    "spell1Id": 4, 
                    "spell2Id": 32, 
                    "summonerName": "Nigh\u0142mare", 
                    "teamId": 200
                }, 
                {
                    "bot": false, 
                    "championId": 67, 
                    "profileIconId": 588, 
                    "spell1Id": 21, 
                    "spell2Id": 4, 
                    "summonerName": "c\u016fbe", 
                    "teamId": 200
                }
            ], 
            "platformId": "EUW1"
        }, 
        {
            "bannedChampions": [], 
            "gameId": 4053948206, 
            "gameLength": 318, 
            "gameMode": "ARAM", 
            "gameQueueConfigId": 450, 
            "gameStartTime": 1559679783509, 
            "gameType": "MATCHED_GAME", 
            "mapId": 12, 
            "observers": {
                "encryptionKey": "iL+AeiARmYIoTQ35eN1HVNC1vxumBfAK"
            }, 
            "participants": [
                {
                    "bot": false, 
                    "championId": 236, 
                    "profileIconId": 563, 
                    "spell1Id": 7, 
                    "spell2Id": 4, 
                    "summonerName": "KayCe", 
                    "teamId": 100
                }, 
                {
                    "bot": false, 
                    "championId": 429, 
                    "profileIconId": 4088, 
                    "spell1Id": 7, 
                    "spell2Id": 4, 
                    "summonerName": "lucktown", 
                    "teamId": 100
                }, 
                {
                    "bot": false, 
                    "championId": 35, 
                    "profileIconId": 4027, 
                    "spell1Id": 14, 
                    "spell2Id": 4, 
                    "summonerName": "mashidi", 
                    "teamId": 100
                }, 
                {
                    "bot": false, 
                    "championId": 79, 
                    "profileIconId": 3478, 
                    "spell1Id": 32, 
                    "spell2Id": 4, 
                    "summonerName": "muyuu", 
                    "teamId": 100
                }, 
                {
                    "bot": false, 
                    "championId": 115, 
                    "profileIconId": 8, 
                    "spell1Id": 4, 
                    "spell2Id": 7, 
                    "summonerName": "Tesonro", 
                    "teamId": 100
                }, 
                {
                    "bot": false, 
                    "championId": 518, 
                    "profileIconId": 902, 
                    "spell1Id": 32, 
                    "spell2Id": 4, 
                    "summonerName": "Capta\u00edn Iglo", 
                    "teamId": 200
                }, 
                {
                    "bot": false, 
                    "championId": 150, 
                    "profileIconId": 588, 
                    "spell1Id": 32, 
                    "spell2Id": 4, 
                    "summonerName": "RetardOfTheYear", 
                    "teamId": 200
                }, 
                {
                    "bot": false, 
                    "championId": 222, 
                    "profileIconId": 4027, 
                    "spell1Id": 4, 
                    "spell2Id": 7, 
                    "summonerName": "R\u00f8rbert\u00f8", 
                    "teamId": 200
                }, 
                {
                    "bot": false, 
                    "championId": 15, 
                    "profileIconId": 3378, 
                    "spell1Id": 4, 
                    "spell2Id": 7, 
                    "summonerName": "Kishini CHL", 
                    "teamId": 200
                }, 
                {
                    "bot": false, 
                    "championId": 13, 
                    "profileIconId": 3872, 
                    "spell1Id": 1, 
                    "spell2Id": 4, 
                    "summonerName": "Uncle Leo", 
                    "teamId": 200
                }
            ], 
            "platformId": "EUW1"
        }, 
        {
            "bannedChampions": [], 
            "gameId": 4053957814, 
            "gameLength": 193, 
            "gameMode": "ARAM", 
            "gameQueueConfigId": 450, 
            "gameStartTime": 1559679908372, 
            "gameType": "MATCHED_GAME", 
            "mapId": 12, 
            "observers": {
                "encryptionKey": "5m3pebOsJiu0BKkFjtrbRNjxytm50iZC"
            }, 
            "participants": [
                {
                    "bot": false, 
                    "championId": 86, 
                    "profileIconId": 1445, 
                    "spell1Id": 32, 
                    "spell2Id": 4, 
                    "summonerName": "Karca\u00efn", 
                    "teamId": 100
                }, 
                {
                    "bot": false, 
                    "championId": 163, 
                    "profileIconId": 1109, 
                    "spell1Id": 3, 
                    "spell2Id": 4, 
                    "summonerName": "c\u00ddph3r", 
                    "teamId": 100
                }, 
                {
                    "bot": false, 
                    "championId": 83, 
                    "profileIconId": 3232, 
                    "spell1Id": 4, 
                    "spell2Id": 32, 
                    "summonerName": "Daggett57", 
                    "teamId": 100
                }, 
                {
                    "bot": false, 
                    "championId": 143, 
                    "profileIconId": 3496, 
                    "spell1Id": 14, 
                    "spell2Id": 4, 
                    "summonerName": "Kahnurame", 
                    "teamId": 100
                }, 
                {
                    "bot": false, 
                    "championId": 28, 
                    "profileIconId": 24, 
                    "spell1Id": 32, 
                    "spell2Id": 4, 
                    "summonerName": "Nejerjelje", 
                    "teamId": 100
                }, 
                {
                    "bot": false, 
                    "championId": 427, 
                    "profileIconId": 3175, 
                    "spell1Id": 3, 
                    "spell2Id": 4, 
                    "summonerName": "July Drizzle", 
                    "teamId": 200
                }, 
                {
                    "bot": false, 
                    "championId": 9, 
                    "profileIconId": 3156, 
                    "spell1Id": 32, 
                    "spell2Id": 4, 
                    "summonerName": "orKs FirEsTorM", 
                    "teamId": 200
                }, 
                {
                    "bot": false, 
                    "championId": 350, 
                    "profileIconId": 4089, 
                    "spell1Id": 3, 
                    "spell2Id": 4, 
                    "summonerName": "lllIIIllIIl", 
                    "teamId": 200
                }, 
                {
                    "bot": false, 
                    "championId": 26, 
                    "profileIconId": 1301, 
                    "spell1Id": 7, 
                    "spell2Id": 4, 
                    "summonerName": "Kondikka", 
                    "teamId": 200
                }, 
                {
                    "bot": false, 
                    "championId": 96, 
                    "profileIconId": 1099, 
                    "spell1Id": 4, 
                    "spell2Id": 7, 
                    "summonerName": "Ak\u00ecles", 
                    "teamId": 200
                }
            ], 
            "platformId": "EUW1"
        }, 
        {
            "bannedChampions": [], 
            "gameId": 4053957374, 
            "gameLength": 131, 
            "gameMode": "ARAM", 
            "gameQueueConfigId": 450, 
            "gameStartTime": 1559679970293, 
            "gameType": "MATCHED_GAME", 
            "mapId": 12, 
            "observers": {
                "encryptionKey": "698i1Trvqu0i05Oud8BYT0amG1roQrXj"
            }, 
            "participants": [
                {
                    "bot": false, 
                    "championId": 63, 
                    "profileIconId": 3898, 
                    "spell1Id": 4, 
                    "spell2Id": 21, 
                    "summonerName": "JuIix", 
                    "teamId": 100
                }, 
                {
                    "bot": false, 
                    "championId": 35, 
                    "profileIconId": 7, 
                    "spell1Id": 32, 
                    "spell2Id": 4, 
                    "summonerName": "kouniabella", 
                    "teamId": 100
                }, 
                {
                    "bot": false, 
                    "championId": 89, 
                    "profileIconId": 715, 
                    "spell1Id": 32, 
                    "spell2Id": 4, 
                    "summonerName": "MemeTrick", 
                    "teamId": 100
                }, 
                {
                    "bot": false, 
                    "championId": 122, 
                    "profileIconId": 3493, 
                    "spell1Id": 32, 
                    "spell2Id": 4, 
                    "summonerName": "Mikozt", 
                    "teamId": 100
                }, 
                {
                    "bot": false, 
                    "championId": 14, 
                    "profileIconId": 563, 
                    "spell1Id": 32, 
                    "spell2Id": 4, 
                    "summonerName": "Mitti", 
                    "teamId": 100
                }, 
                {
                    "bot": false, 
                    "championId": 104, 
                    "profileIconId": 3202, 
                    "spell1Id": 3, 
                    "spell2Id": 4, 
                    "summonerName": "Drusalinka", 
                    "teamId": 200
                }, 
                {
                    "bot": false, 
                    "championId": 236, 
                    "profileIconId": 4088, 
                    "spell1Id": 4, 
                    "spell2Id": 7, 
                    "summonerName": "TheSpecialJ", 
                    "teamId": 200
                }, 
                {
                    "bot": false, 
                    "championId": 497, 
                    "profileIconId": 3478, 
                    "spell1Id": 4, 
                    "spell2Id": 32, 
                    "summonerName": "Romerbach", 
                    "teamId": 200
                }, 
                {
                    "bot": false, 
                    "championId": 127, 
                    "profileIconId": 676, 
                    "spell1Id": 4, 
                    "spell2Id": 32, 
                    "summonerName": "420 SYSTEM ERROR", 
                    "teamId": 200
                }, 
                {
                    "bot": false, 
                    "championId": 11, 
                    "profileIconId": 3182, 
                    "spell1Id": 32, 
                    "spell2Id": 4, 
                    "summonerName": "qiongmei", 
                    "teamId": 200
                }
            ], 
            "platformId": "EUW1"
        }, 
        {
            "bannedChampions": [
                {
                    "championId": 30, 
                    "pickTurn": 1, 
                    "teamId": 100
                }, 
                {
                    "championId": 240, 
                    "pickTurn": 2, 
                    "teamId": 100
                }, 
                {
                    "championId": 412, 
                    "pickTurn": 3, 
                    "teamId": 100
                }, 
                {
                    "championId": 350, 
                    "pickTurn": 4, 
                    "teamId": 100
                }, 
                {
                    "championId": 39, 
                    "pickTurn": 5, 
                    "teamId": 100
                }, 
                {
                    "championId": 421, 
                    "pickTurn": 6, 
                    "teamId": 200
                }, 
                {
                    "championId": 119, 
                    "pickTurn": 7, 
                    "teamId": 200
                }, 
                {
                    "championId": 350, 
                    "pickTurn": 8, 
                    "teamId": 200
                }, 
                {
                    "championId": 266, 
                    "pickTurn": 9, 
                    "teamId": 200
                }, 
                {
                    "championId": 30, 
                    "pickTurn": 10, 
                    "teamId": 200
                }
            ], 
            "gameId": 4053919065, 
            "gameLength": 186, 
            "gameMode": "CLASSIC", 
            "gameQueueConfigId": 420, 
            "gameStartTime": 1559679915149, 
            "gameType": "MATCHED_GAME", 
            "mapId": 11, 
            "observers": {
                "encryptionKey": "bDmpAMN9K8GkL6Bdhxc++JIAHqlSHpml"
            }, 
            "participants": [
                {
                    "bot": false, 
                    "championId": 517, 
                    "profileIconId": 3478, 
                    "spell1Id": 4, 
                    "spell2Id": 12, 
                    "summonerName": "mavi bir kumru", 
                    "teamId": 100
                }, 
                {
                    "bot": false, 
                    "championId": 9, 
                    "profileIconId": 22, 
                    "spell1Id": 4, 
                    "spell2Id": 14, 
                    "summonerName": "GRE Salah", 
                    "teamId": 100
                }, 
                {
                    "bot": false, 
                    "championId": 15, 
                    "profileIconId": 7, 
                    "spell1Id": 4, 
                    "spell2Id": 12, 
                    "summonerName": "DASSADSQWDASDASD", 
                    "teamId": 100
                }, 
                {
                    "bot": false, 
                    "championId": 91, 
                    "profileIconId": 1449, 
                    "spell1Id": 4, 
                    "spell2Id": 14, 
                    "summonerName": "DP Pbd", 
                    "teamId": 100
                }, 
                {
                    "bot": false, 
                    "championId": 64, 
                    "profileIconId": 4084, 
                    "spell1Id": 4, 
                    "spell2Id": 11, 
                    "summonerName": "Kadiertje", 
                    "teamId": 100
                }, 
                {
                    "bot": false, 
                    "championId": 38, 
                    "profileIconId": 575, 
                    "spell1Id": 12, 
                    "spell2Id": 4, 
                    "summonerName": "DK Chapapi", 
                    "teamId": 200
                }, 
                {
                    "bot": false, 
                    "championId": 99, 
                    "profileIconId": 3002, 
                    "spell1Id": 14, 
                    "spell2Id": 4, 
                    "summonerName": "brain lag sry", 
                    "teamId": 200
                }, 
                {
                    "bot": false, 
                    "championId": 81, 
                    "profileIconId": 23, 
                    "spell1Id": 4, 
                    "spell2Id": 7, 
                    "summonerName": "sQ\u00fbiiRReL", 
                    "teamId": 200
                }, 
                {
                    "bot": false, 
                    "championId": 203, 
                    "profileIconId": 4088, 
                    "spell1Id": 11, 
                    "spell2Id": 4, 
                    "summonerName": "G2 Jerkz", 
                    "teamId": 200
                }, 
                {
                    "bot": false, 
                    "championId": 13, 
                    "profileIconId": 4100, 
                    "spell1Id": 12, 
                    "spell2Id": 4, 
                    "summonerName": "Maikokoro", 
                    "teamId": 200
                }
            ], 
            "platformId": "EUW1"
        }
    ]
}